mkdocs_click/__init__.py
mkdocs_click/__version__.py
mkdocs_click/_docs.py
mkdocs_click/_exceptions.py
mkdocs_click/_extension.py
mkdocs_click/_loader.py
mkdocs_click/_processing.py
mkdocs_click/py.typed
mkdocs_click-0.8.1.dist-info/METADATA
mkdocs_click-0.8.1.dist-info/WHEEL
mkdocs_click-0.8.1.dist-info/entry_points.txt
mkdocs_click-0.8.1.dist-info/licenses/LICENSE
mkdocs_click-0.8.1.dist-info/RECORD
