Metadata-Version: 2.1
Name: mkdocs-click
Version: 0.8.1
Summary: An MkDocs extension to generate documentation for Click command line applications
Project-URL: Source, https://github.com/mkdocs/mkdocs-click
Project-URL: Issues, https://github.com/mkdocs/mkdocs-click/issues
Project-URL: Changelog, https://github.com/mkdocs/mkdocs-click/blob/master/CHANGELOG.md
Author-email: Datadog <packages@datadoghq.com>
License-Expression: Apache-2.0
License-File: LICENSE
Keywords: click,datadog,mkdocs,mkdocs-plugin
Classifier: Development Status :: 4 - Beta
Classifier: Environment :: Console
Classifier: Environment :: Web Environment
Classifier: Intended Audience :: Developers
Classifier: License :: OSI Approved :: Apache Software License
Classifier: Operating System :: OS Independent
Classifier: Programming Language :: Python
Classifier: Programming Language :: Python :: 3.7
Classifier: Programming Language :: Python :: 3.8
Classifier: Programming Language :: Python :: 3.9
Classifier: Programming Language :: Python :: 3.10
Classifier: Programming Language :: Python :: 3.11
Classifier: Topic :: Documentation
Classifier: Topic :: Software Development :: Documentation
Classifier: Topic :: Text Processing :: Markup :: Markdown
Classifier: Typing :: Typed
Requires-Python: >=3.7
Requires-Dist: click>=8.1
Requires-Dist: markdown>=3.3
